hsutools/__init__.py
hsutools/cli.py
hsutools/config.py
hsutools/core/__init__.py
hsutools/core/create_path.py
hsutools/core/docx_to_pdf.py
hsutools/core/file_manage.py
hsutools/core/file_renamer.py
hsutools/utils.py
hsutools-1.0.4.dist-info/METADATA
hsutools-1.0.4.dist-info/WHEEL
hsutools-1.0.4.dist-info/entry_points.txt
hsutools-1.0.4.dist-info/licenses/LICENSE
hsutools-1.0.4.dist-info/RECORD
