Metadata-Version: 2.4
Name: hsutools
Version: 1.0.4
Summary: Utilities for directory readme generation, file management, renaming, and docx to pdf conversion.
License: MIT
License-File: LICENSE
Author: hsutools maintainers
Requires-Python: >=3.10,<3.14
Classifier: License :: OSI Approved :: MIT License
Classifier: Programming Language :: Python :: 3
Classifier: Programming Language :: Python :: 3.10
Classifier: Programming Language :: Python :: 3.11
Classifier: Programming Language :: Python :: 3.12
Classifier: Programming Language :: Python :: 3.13
Requires-Dist: click (>=8.1.7,<8.2)
Requires-Dist: docx2pdf (>=0.1.8,<0.2.0)
Requires-Dist: tabulate (>=0.9.0,<0.10.0)
Requires-Dist: typer[all] (>=0.12.5,<0.13.0)
